a9a2jkf2/__init__.c
a9a2jkf2/__init__.cp312-win_amd64.pyd
a9a2jkf2/__init__.py
9a2jkf2-0.0.1.dist-info/METADATA
9a2jkf2-0.0.1.dist-info/WHEEL
9a2jkf2-0.0.1.dist-info/top_level.txt
9a2jkf2-0.0.1.dist-info/RECORD
