Metadata-Version: 2.4
Name: 9a2jkf2
Version: 0.0.1
Summary: Python enc*^"*&£^$
Author-email: Janet Smithson <alex@gmail.com>
License: MIT
Requires-Python: >=3.8
